rtl/control_unit.v
// control_unit.v - Control Unit
// Decodes instructions and generates control signals for other components

module control_unit (
    input clk,                    // Clock signal
    input rst,                    // Reset signal
    input [7:0] instruction,      // Current instruction from memory
    input zero_flag,              // Zero flag from ALU
    output reg pc_enable,         // Enable PC increment
    output reg pc_load,           // Load new PC value (for jumps)
    output reg reg_write_enable,  // Enable register write
    output reg [2:0] alu_op,      // ALU operation select
    output reg halt               // Halt signal (stop CPU)
);

    // Instruction format: {4-bit opcode, 4-bit operand}
    wire [3:0] opcode = instruction[7:4];
    wire [3:0] operand = instruction[3:0];
    
    // Opcode definitions
    localparam OP_LOAD = 4'b0000;  // Load immediate value
    localparam OP_STORE = 4'b0001; // Store (not implemented in this simple version)
    localparam OP_ADD  = 4'b0010;  // Add
    localparam OP_SUB  = 4'b0011;  // Subtract
    localparam OP_AND  = 4'b0100;  // Bitwise AND
    localparam OP_OR   = 4'b0101;  // Bitwise OR
    localparam OP_JUMP = 4'b0110;  // Unconditional jump
    localparam OP_HALT = 4'b0111;  // Halt execution
    
    // State machine for instruction execution
    localparam STATE_FETCH = 2'b00;
    localparam STATE_DECODE = 2'b01;
    localparam STATE_EXECUTE = 2'b10;
    localparam STATE_HALT = 2'b11;
    
    reg [1:0] state;
    
    always @(posedge clk or posedge rst) begin
        if (rst) begin
            state <= STATE_FETCH;
            pc_enable <= 0;
            pc_load <= 0;
            reg_write_enable <= 0;
            alu_op <= 3'b000;
            halt <= 0;
        end else begin
            case (state)
                STATE_FETCH: begin
                    // Fetch instruction (already done by instruction memory)
                    pc_enable <= 0;
                    pc_load <= 0;
                    reg_write_enable <= 0;
                    state <= STATE_DECODE;
                end
                
                STATE_DECODE: begin
                    // Decode and execute instruction
                    case (opcode)
                        OP_LOAD: begin
                            // Load immediate value into R0
                            alu_op <= 3'b101;  // PASS operand through ALU
                            reg_write_enable <= 1;
                            pc_enable <= 1;
                            pc_load <= 0;
                            state <= STATE_FETCH;
                        end
                        
                        OP_ADD: begin
                            // Add operation
                            alu_op <= 3'b000;  // ADD
                            reg_write_enable <= 1;
                            pc_enable <= 1;
                            pc_load <= 0;
                            state <= STATE_FETCH;
                        end
                        
                        OP_SUB: begin
                            // Subtract operation
                            alu_op <= 3'b001;  // SUB
                            reg_write_enable <= 1;
                            pc_enable <= 1;
                            pc_load <= 0;
                            state <= STATE_FETCH;
                        end
                        
                        OP_AND: begin
                            // AND operation
                            alu_op <= 3'b010;  // AND
                            reg_write_enable <= 1;
                            pc_enable <= 1;
                            pc_load <= 0;
                            state <= STATE_FETCH;
                        end
                        
                        OP_OR: begin
                            // OR operation
                            alu_op <= 3'b011;  // OR
                            reg_write_enable <= 1;
                            pc_enable <= 1;
                            pc_load <= 0;
                            state <= STATE_FETCH;
                        end
                        
                        OP_JUMP: begin
                            // Jump to address
                            pc_load <= 1;
                            pc_enable <= 0;
                            reg_write_enable <= 0;
                            state <= STATE_FETCH;
                        end
                        
                        OP_HALT: begin
                            // Halt execution
                            halt <= 1;
                            pc_enable <= 0;
                            pc_load <= 0;
                            reg_write_enable <= 0;
                            state <= STATE_HALT;
                        end
                        
                        default: begin
                            // Unknown instruction - treat as NOP
                            pc_enable <= 1;
                            pc_load <= 0;
                            reg_write_enable <= 0;
                            state <= STATE_FETCH;
                        end
                    endcase
                end
                
                STATE_HALT: begin
                    // Stay halted
                    halt <= 1;
                    pc_enable <= 0;
                    pc_load <= 0;
                    reg_write_enable <= 0;
                    state <= STATE_HALT;
                end
                
                default: begin
                    state <= STATE_FETCH;
                end
            endcase
        end
    end

endmodule

rtl/alu.v
// alu.v - Arithmetic Logic Unit
// Performs arithmetic and logical operations

module alu (
    input  [3:0] operand_a,      // First operand (4 bits)
    input  [3:0] operand_b,      // Second operand (4 bits)
    input  [2:0] alu_op,         // Operation select (3 bits)
    output reg [3:0] result,     // Result (4 bits)
    output reg zero_flag         // Flag: 1 if result is zero
);

    // ALU Operations
    localparam ALU_ADD  = 3'b000;  // Addition
    localparam ALU_SUB  = 3'b001;  // Subtraction
    localparam ALU_AND  = 3'b010;  // Bitwise AND
    localparam ALU_OR   = 3'b011;  // Bitwise OR
    localparam ALU_XOR  = 3'b100;  // Bitwise XOR
    localparam ALU_PASS = 3'b101;  // Pass operand_a through

    always @(*) begin
        case (alu_op)
            ALU_ADD:  result = operand_a + operand_b;
            ALU_SUB:  result = operand_a - operand_b;
            ALU_AND:  result = operand_a & operand_b;
            ALU_OR:   result = operand_a | operand_b;
            ALU_XOR:  result = operand_a ^ operand_b;
            ALU_PASS: result = operand_a;
            default:  result = 4'b0000;
        endcase
        
        // Set zero flag if result is zero
        zero_flag = (result == 4'b0000);
    end

endmodule

rtl/register_file.v
// register_file.v - Register File
// Contains 4 registers (R0, R1, R2, R3) that store 4-bit values

module register_file (
    input clk,                    // Clock signal
    input rst,                    // Reset signal (active high)
    input write_enable,           // Write enable: 1 to write, 0 to read only
    input  [1:0] read_addr_a,     // Address of first register to read (2 bits = 4 registers)
    input  [1:0] read_addr_b,     // Address of second register to read
    input  [1:0] write_addr,      // Address of register to write to
    input  [3:0] write_data,      // Data to write (4 bits)
    output [3:0] read_data_a,     // Data read from first register
    output [3:0] read_data_b      // Data read from second register
);

    // 4 registers, each 4 bits wide
    reg [3:0] registers [0:3];
    
    // Read operations (combinational - happens immediately)
    assign read_data_a = registers[read_addr_a];
    assign read_data_b = registers[read_addr_b];
    
    // Write operation (sequential - happens on clock edge)
    always @(posedge clk or posedge rst) begin
        if (rst) begin
            // Reset all registers to 0
            registers[0] <= 4'b0000;
            registers[1] <= 4'b0000;
            registers[2] <= 4'b0000;
            registers[3] <= 4'b0000;
        end else if (write_enable) begin
            // Write data to specified register
            registers[write_addr] <= write_data;
        end
    end

endmodule

rtl/instruction_memory.v
// instruction_memory.v - Instruction Memory
// Stores the program instructions (ROM - Read Only Memory)

module instruction_memory (
    input  [3:0] address,         // Instruction address (4 bits = 16 instructions max)
    output [7:0] instruction      // 8-bit instruction (4-bit opcode + 4-bit operand)
);

    // Memory array: 16 locations, each 8 bits wide
    reg [7:0] memory [0:15];
    
    // Initialize with a sample program
    initial begin
        // Simple program to demonstrate CPU functionality
        // Format: {4-bit opcode, 4-bit operand/address}
        
        memory[0]  = 8'b0000_0101;  // LOAD R0, 5      - Load immediate value 5 into R0
        memory[1]  = 8'b0000_0011;  // LOAD R1, 3      - Load immediate value 3 into R1
        memory[2]  = 8'b0010_0001;  // ADD R0, R1      - R0 = R0 + R1 (5 + 3 = 8)
        memory[3]  = 8'b0000_0010;  // LOAD R2, 2      - Load immediate value 2 into R2
        memory[4]  = 8'b0011_0010;  // SUB R0, R2      - R0 = R0 - R2 (8 - 2 = 6)
        memory[5]  = 8'b0100_0001;  // AND R0, R1      - R0 = R0 & R1 (bitwise AND)
        memory[6]  = 8'b0101_0001;  // OR R0, R1       - R0 = R0 | R1 (bitwise OR)
        memory[7]  = 8'b0111_0000;  // HALT            - Stop execution
        memory[8]  = 8'b0000_0000;  // NOP (unused)
        memory[9]  = 8'b0000_0000;  // NOP (unused)
        memory[10] = 8'b0000_0000;  // NOP (unused)
        memory[11] = 8'b0000_0000;  // NOP (unused)
        memory[12] = 8'b0000_0000;  // NOP (unused)
        memory[13] = 8'b0000_0000;  // NOP (unused)
        memory[14] = 8'b0000_0000;  // NOP (unused)
        memory[15] = 8'b0000_0000;  // NOP (unused)
    end
    
    // Read instruction at given address
    assign instruction = memory[address];

endmodule

rtl/program_counter.v
// program_counter.v - Program Counter
// Keeps track of the current instruction address

module program_counter (
    input clk,                    // Clock signal
    input rst,                    // Reset signal (active high)
    input enable,                 // Enable counting (1 = increment, 0 = hold)
    input load,                   // Load new address (for jumps)
    input [3:0] load_addr,        // Address to load (for jump instructions)
    output reg [3:0] pc           // Current program counter value (4 bits = 16 addresses)
);

    always @(posedge clk or posedge rst) begin
        if (rst) begin
            // Reset PC to 0 (start of program)
            pc <= 4'b0000;
        end else if (load) begin
            // Load new address (for jump instructions)
            pc <= load_addr;
        end else if (enable) begin
            // Increment PC to next instruction
            pc <= pc + 1;
        end
        // If neither load nor enable, PC holds its value
    end

endmodule

rtl/cpu.v
// cpu.v - Top-Level CPU Module
// Connects all components: ALU, Register File, Program Counter, Instruction Memory, Control Unit

module cpu (
    input clk,              // Clock signal
    input rst,              // Reset signal
    output halt,            // Halt signal (1 when program finishes)
    output [3:0] pc_out,    // Current PC value (for debugging)
    output [3:0] reg0_out,  // R0 value (for debugging)
    output [3:0] reg1_out,  // R1 value (for debugging)
    output [3:0] reg2_out,  // R2 value (for debugging)
    output [3:0] reg3_out   // R3 value (for debugging)
);

    // Internal wires
    wire [3:0] pc;                  // Program counter
    wire [7:0] instruction;         // Current instruction
    wire [3:0] alu_result;          // ALU output
    wire zero_flag;                 // ALU zero flag
    wire [3:0] reg_read_a;          // Register file output A
    wire [3:0] reg_read_b;          // Register file output B
    wire pc_enable;                 // PC increment enable
    wire pc_load;                   // PC load enable
    wire reg_write_enable;          // Register write enable
    wire [2:0] alu_op;              // ALU operation
    
    // Extract operand from instruction for immediate values
    wire [3:0] immediate = instruction[3:0];
    
    // For this simple CPU, we always write to R0 and read from R0 and R1
    wire [1:0] write_addr = 2'b00;  // Always write to R0
    wire [1:0] read_addr_a = 2'b00; // Always read R0
    wire [1:0] read_addr_b = 2'b01; // Always read R1
    
    // Program Counter
    program_counter pc_unit (
        .clk(clk),
        .rst(rst),
        .enable(pc_enable),
        .load(pc_load),
        .load_addr(immediate),
        .pc(pc)
    );
    
    // Instruction Memory
    instruction_memory imem (
        .address(pc),
        .instruction(instruction)
    );
    
    // Register File
    register_file reg_file (
        .clk(clk),
        .rst(rst),
        .write_enable(reg_write_enable),
        .read_addr_a(read_addr_a),
        .read_addr_b(read_addr_b),
        .write_addr(write_addr),
        .write_data(alu_result),
        .read_data_a(reg_read_a),
        .read_data_b(reg_read_b)
    );
    
    // ALU
    alu alu_unit (
        .operand_a(reg_read_a),
        .operand_b(instruction[7:4] == 4'b0000 ? immediate : reg_read_b), // Use immediate for LOAD
        .alu_op(alu_op),
        .result(alu_result),
        .zero_flag(zero_flag)
    );
    
    // Control Unit
    control_unit control (
        .clk(clk),
        .rst(rst),
        .instruction(instruction),
        .zero_flag(zero_flag),
        .pc_enable(pc_enable),
        .pc_load(pc_load),
        .reg_write_enable(reg_write_enable),
        .alu_op(alu_op),
        .halt(halt)
    );
    
    // Debug outputs
    assign pc_out = pc;
    
    // Connect register outputs for debugging
    assign reg0_out = reg_file.registers[0];
    assign reg1_out = reg_file.registers[1];
    assign reg2_out = reg_file.registers[2];
    assign reg3_out = reg_file.registers[3];

endmodule

sim/cpu_tb.v
// cpu_tb.v - CPU Testbench
// Simulates the CPU and generates waveforms for debugging

`timescale 1ns/1ps

module cpu_tb;

    // Testbench signals
    reg clk;
    reg rst;
    wire halt;
    wire [3:0] pc_out;
    wire [3:0] reg0_out;
    wire [3:0] reg1_out;
    wire [3:0] reg2_out;
    wire [3:0] reg3_out;
    
    // Instantiate the CPU
    cpu cpu_inst (
        .clk(clk),
        .rst(rst),
        .halt(halt),
        .pc_out(pc_out),
        .reg0_out(reg0_out),
        .reg1_out(reg1_out),
        .reg2_out(reg2_out),
        .reg3_out(reg3_out)
    );
    
    // Clock generation: 10ns period (100MHz)
    initial begin
        clk = 0;
        forever #5 clk = ~clk;
    end
    
    // Test sequence
    initial begin
        // Create VCD file for waveform viewing
        $dumpfile("cpu_sim.vcd");
        $dumpvars(0, cpu_tb);
        
        // Display header
        $display("=================================================");
        $display("    Simple 4-bit CPU Simulation");
        $display("=================================================");
        $display("Time(ns) | PC | Halt | R0 | R1 | R2 | R3 | Instruction");
        $display("-------------------------------------------------");
        
        // Reset sequence
        rst = 1;
        #20;  // Hold reset for 20ns
        rst = 0;
        
        // Monitor signals during execution
        repeat (50) begin
            @(posedge clk);
            #1; // Small delay to see values after clock edge
            $display("%7t |  %d |   %b  | %2d | %2d | %2d | %2d | %b", 
                     $time, pc_out, halt, reg0_out, reg1_out, reg2_out, reg3_out,
                     cpu_inst.instruction);
            
            // Stop if CPU halts
            if (halt) begin
                $display("-------------------------------------------------");
                $display("CPU HALTED at time %0t ns", $time);
                $display("=================================================");
                $display("Final Register Values:");
                $display("  R0 = %d (binary: %b)", reg0_out, reg0_out);
                $display("  R1 = %d (binary: %b)", reg1_out, reg1_out);
                $display("  R2 = %d (binary: %b)", reg2_out, reg2_out);
                $display("  R3 = %d (binary: %b)", reg3_out, reg3_out);
                $display("=================================================");
                #20;
                $finish;
            end
        end
        
        // If we get here, CPU didn't halt
        $display("WARNING: CPU did not halt after 50 cycles");
        $finish;
    end
    
    // Timeout watchdog (in case something goes wrong)
    initial begin
        #5000;  // 5000ns timeout
        $display("ERROR: Simulation timeout!");
        $finish;
    end

endmodule

cpu_sim.vcd
$date
	Thu Dec 11 15:52:34 2025
$end
$version
	Icarus Verilog
$end
$timescale
	1ps
$end
$scope module cpu_tb $end
$var wire 4 ! reg3_out [3:0] $end
$var wire 4 " reg2_out [3:0] $end
$var wire 4 # reg1_out [3:0] $end
$var wire 4 $ reg0_out [3:0] $end
$var wire 4 % pc_out [3:0] $end
$var wire 1 & halt $end
$var reg 1 ' clk $end
$var reg 1 ( rst $end
$scope module cpu_inst $end
$var wire 1 ' clk $end
$var wire 4 ) pc_out [3:0] $end
$var wire 2 * read_addr_a [1:0] $end
$var wire 2 + read_addr_b [1:0] $end
$var wire 4 , reg0_out [3:0] $end
$var wire 4 - reg1_out [3:0] $end
$var wire 4 . reg2_out [3:0] $end
$var wire 4 / reg3_out [3:0] $end
$var wire 1 ( rst $end
$var wire 2 0 write_addr [1:0] $end
$var wire 1 1 zero_flag $end
$var wire 1 2 reg_write_enable $end
$var wire 4 3 reg_read_b [3:0] $end
$var wire 4 4 reg_read_a [3:0] $end
$var wire 1 5 pc_load $end
$var wire 1 6 pc_enable $end
$var wire 4 7 pc [3:0] $end
$var wire 8 8 instruction [7:0] $end
$var wire 4 9 immediate [3:0] $end
$var wire 1 & halt $end
$var wire 4 : alu_result [3:0] $end
$var wire 3 ; alu_op [2:0] $end
$scope module alu_unit $end
$var wire 4 < operand_b [3:0] $end
$var wire 4 = operand_a [3:0] $end
$var wire 3 > alu_op [2:0] $end
$var parameter 3 ? ALU_ADD $end
$var parameter 3 @ ALU_AND $end
$var parameter 3 A ALU_OR $end
$var parameter 3 B ALU_PASS $end
$var parameter 3 C ALU_SUB $end
$var parameter 3 D ALU_XOR $end
$var reg 4 E result [3:0] $end
$var reg 1 1 zero_flag $end
$upscope $end
$scope module control $end
$var wire 1 ' clk $end
$var wire 1 ( rst $end
$var wire 1 1 zero_flag $end
$var wire 4 F operand [3:0] $end
$var wire 4 G opcode [3:0] $end
$var wire 8 H instruction [7:0] $end
$var parameter 4 I OP_ADD $end
$var parameter 4 J OP_AND $end
$var parameter 4 K OP_HALT $end
$var parameter 4 L OP_JUMP $end
$var parameter 4 M OP_LOAD $end
$var parameter 4 N OP_OR $end
$var parameter 4 O OP_STORE $end
$var parameter 4 P OP_SUB $end
$var parameter 2 Q STATE_DECODE $end
$var parameter 2 R STATE_EXECUTE $end
$var parameter 2 S STATE_FETCH $end
$var parameter 2 T STATE_HALT $end
$var reg 3 U alu_op [2:0] $end
$var reg 1 & halt $end
$var reg 1 6 pc_enable $end
$var reg 1 5 pc_load $end
$var reg 1 2 reg_write_enable $end
$var reg 2 V state [1:0] $end
$upscope $end
$scope module imem $end
$var wire 8 W instruction [7:0] $end
$var wire 4 X address [3:0] $end
$upscope $end
$scope module pc_unit $end
$var wire 1 ' clk $end
$var wire 1 6 enable $end
$var wire 1 5 load $end
$var wire 4 Y load_addr [3:0] $end
$var wire 1 ( rst $end
$var reg 4 Z pc [3:0] $end
$upscope $end
$scope module reg_file $end
$var wire 1 ' clk $end
$var wire 2 [ read_addr_a [1:0] $end
$var wire 2 \ read_addr_b [1:0] $end
$var wire 4 ] read_data_a [3:0] $end
$var wire 4 ^ read_data_b [3:0] $end
$var wire 1 ( rst $end
$var wire 2 _ write_addr [1:0] $end
$var wire 4 ` write_data [3:0] $end
$var wire 1 2 write_enable $end
$upscope $end
$upscope $end
$upscope $end
$enddefinitions $end
$comment Show the parameter values. $end
$dumpall
b11 T
b0 S
b10 R
b1 Q
b11 P
b1 O
b101 N
b0 M
b110 L
b111 K
b100 J
b10 I
b100 D
b1 C
b101 B
b11 A
b10 @
b0 ?
$end
#0
$dumpvars
b101 `
b0 _
b0 ^
b0 ]
b1 \
b0 [
b0 Z
b101 Y
b0 X
b101 W
b0 V
b0 U
b101 H
b0 G
b101 F
b101 E
b0 >
b0 =
b101 <
b0 ;
b101 :
b101 9
b101 8
b0 7
06
05
b0 4
b0 3
02
01
b0 0
b0 /
b0 .
b0 -
b0 ,
b1 +
b0 *
b0 )
1(
0'
0&
b0 %
b0 $
b0 #
b0 "
b0 !
$end
#5000
1'
#10000
0'
#15000
1'
#20000
0'
0(
#25000
b1 V
1'
#30000
0'
#35000
11
b0 :
b0 E
b0 `
b0 V
16
12
b101 ;
b101 >
b101 U
1'
#40000
0'
#45000
b11 <
b11 F
b11 9
b11 Y
b1 V
02
06
b11 8
b11 H
b11 W
b1 %
b1 )
b1 7
b1 X
b1 Z
1'
#50000
0'
#55000
b0 V
16
12
1'
#60000
0'
#65000
b0 <
b1 F
b10 G
b1 9
b1 Y
b1 V
02
06
b100001 8
b100001 H
b100001 W
b10 %
b10 )
b10 7
b10 X
b10 Z
1'
#70000
0'
#75000
b0 V
16
12
b0 ;
b0 >
b0 U
1'
#80000
0'
#85000
01
b10 :
b10 E
b10 `
b10 <
b10 F
b0 G
b10 9
b10 Y
b1 V
02
06
b10 8
b10 H
b10 W
b11 %
b11 )
b11 7
b11 X
b11 Z
1'
#90000
0'
#95000
11
b0 :
b0 E
b0 `
b0 V
16
12
b101 ;
b101 >
b101 U
1'
#100000
0'
#105000
b0 <
b11 G
b1 V
02
06
b110010 8
b110010 H
b110010 W
b100 %
b100 )
b100 7
b100 X
b100 Z
1'
#110000
0'
#115000
b0 V
16
12
b1 ;
b1 >
b1 U
1'
#120000
0'
#125000
b1 F
b100 G
b1 9
b1 Y
b1 V
02
06
b1000001 8
b1000001 H
b1000001 W
b101 %
b101 )
b101 7
b101 X
b101 Z
1'
#130000
0'
#135000
b0 V
16
12
b10 ;
b10 >
b10 U
1'
#140000
0'
#145000
b101 G
b1 V
02
06
b1010001 8
b1010001 H
b1010001 W
b110 %
b110 )
b110 7
b110 X
b110 Z
1'
#150000
0'
#155000
b0 V
16
12
b11 ;
b11 >
b11 U
1'
#160000
0'
#165000
b0 F
b111 G
b0 9
b0 Y
b1 V
02
06
b1110000 8
b1110000 H
b1110000 W
b111 %
b111 )
b111 7
b111 X
b111 Z
1'
#170000
0'
#175000
b11 V
1&
1'
